py_lib/TOPSISRAGHAVAN1019013636.py
py_lib/__init__.py
TOPSISRAGHAVAN101903636-0.0.0.dist-info/LICENSE
TOPSISRAGHAVAN101903636-0.0.0.dist-info/METADATA
TOPSISRAGHAVAN101903636-0.0.0.dist-info/WHEEL
TOPSISRAGHAVAN101903636-0.0.0.dist-info/top_level.txt
TOPSISRAGHAVAN101903636-0.0.0.dist-info/RECORD
