Metadata-Version: 2.1
Name: TOPSISRAGHAVAN101903636
Version: 0.0.0
Summary: TOPSISRAGHAVAN101903636
Author: RaghavanMarwaha
Author-email: rmarwaha_be19@thapar.edu
License: UNKNOWN
Keywords: python,topsis
Platform: UNKNOWN
Classifier: Development Status :: 1 - Planning
Classifier: Intended Audience :: Developers
Classifier: Programming Language :: Python :: 3
Classifier: Operating System :: Unix
Classifier: Operating System :: MacOS :: MacOS X
Classifier: Operating System :: Microsoft :: Windows
License-File: LICENSE
